HW/hw2/src/shift_reg.sv
`timescale 1ns / 10ps

module shift_reg #(
    parameter DATA_W = 8
) (
    input logic clk,
    reset,
    shift_en,
    input logic [DATA_W-1:0] data_in,
    output logic [DATA_W-1:0] data_out
);

  // Array of registers for internal stages as hinted
  logic [DATA_W-1:0] stages[3:0];

  always_ff @(posedge clk) begin
    if (reset) begin
      stages[0] <= '0;
      stages[1] <= '0;
      stages[2] <= '0;
      stages[3] <= '0;
    end else if (shift_en) begin
      stages[0] <= data_in;
      stages[1] <= stages[0];
      stages[2] <= stages[1];
      stages[3] <= stages[2];
    end
    // If shift_en == 0, state is naturally held in always_ff
  end

  // Continuous assignment to the output port
  assign data_out = stages[3];

endmodule

HW/hw2/src/shift_reg_tb.sv
`timescale 1ns / 10ps

module shift_reg_tb;

  // Inputs to the DUT are declared as 'reg'
  reg clk;
  reg reset;
  reg shift_en;
  reg [7:0] data_in;

  // Outputs from the DUT are declared as 'wire'
  wire [7:0] data_out;  // Assumed 8-bit output, adjust if your module differs

  // match your actual Verilog design file.
  shift_reg dut (
      .clk(clk),
      .reset(reset),
      .shift_en(shift_en),
      .data_in(data_in),
      .data_out(data_out)
  );

  // Generates a clock with a 10ns period, matching the #10 step delays in your stimulus
  initial begin
    clk = 0;
    forever #5 clk = ~clk;
  end

  // Your Stimulus Block
  initial begin
    // Dumpfile setup for "shift.vcd"
    $dumpfile("shift.vcd");
    // Adjusted to match the testbench module name 'shift_reg_tb'
    $dumpvars(0, shift_reg_tb);

    // Reset sequence
    reset = 1;
    shift_en = 0;
    data_in = 8'hAA;
    #15;
    reset = 0;

    // Cycles 1-4: shift_en = 1, incrementing data_in
    shift_en = 1;
    data_in = 8'h11;
    #10;
    data_in = 8'h22;
    #10;
    data_in = 8'h33;
    #10;
    data_in = 8'h44;
    #10;

    // Cycles 5-6: shift_en = 0 (hold state)
    shift_en = 0;
    #20;

    // Cycle 7: shift_en = 1, data_in = 8'hFF
    shift_en = 1;
    data_in  = 8'hFF;
    #10;

    // Wait remaining time to hit 100ns total simulation time
    // Time elapsed: 15 (reset) + 40 (c1-4) + 20 (c5-6) + 10 (c7) = 85ns
    #15;

    $finish;
  end

endmodule

HW/hw2/shift.vcd
$date
	Mon Mar  2 14:41:26 2026
$end

$version
	Synopsys VCS version V-2023.12-SP2-1_Full64
$end

$timescale
	10ps
$end

$comment Csum: 1 f1a747aeb1c27f78 $end


$scope module shift_reg_tb $end
$var reg 1 ! clk $end
$var reg 1 " reset $end
$var reg 1 # shift_en $end
$var reg 8 $ data_in [7:0] $end
$var wire 8 % data_out [7:0] $end

$scope module dut $end
$var reg 1 & clk $end
$var reg 1 ' reset $end
$var reg 1 ( shift_en $end
$var reg 8 ) data_in [7:0] $end
$var reg 8 * data_out [7:0] $end
$upscope $end

$upscope $end

$enddefinitions $end

#0
$dumpvars
0!
1'
0(
1"
0#
b10101010 $
bxxxxxxxx %
b10101010 )
bxxxxxxxx *
0&
$end
#500
1!
1&
b00000000 *
b00000000 %
#1000
0!
0&
#1500
0"
0'
1#
1(
b00010001 $
b00010001 )
1!
1&
#2000
0!
0&
#2500
b00100010 $
b00100010 )
1!
1&
#3000
0!
0&
#3500
b00110011 $
b00110011 )
1!
1&
#4000
0!
0&
#4500
b01000100 $
b01000100 )
1!
1&
b00010001 *
b00010001 %
#5000
0!
0&
#5500
0#
0(
1!
1&
#6000
0!
0&
#6500
1!
1&
#7000
0!
0&
#7500
1#
1(
b11111111 $
b11111111 )
1!
1&
b00100010 *
b00100010 %
#8000
0!
0&
#8500
1!
1&
b00110011 *
b00110011 %
#9000
0!
0&
#9500
1!
1&
b01000100 *
b01000100 %
